README.md
setup.cfg
setup.py
lpl/__init__.py
lpl/lpl.py
lpl/zabbix_logger.py
ourLittleLogger.egg-info/PKG-INFO
ourLittleLogger.egg-info/SOURCES.txt
ourLittleLogger.egg-info/dependency_links.txt
ourLittleLogger.egg-info/requires.txt
ourLittleLogger.egg-info/top_level.txt