Metadata-Version: 1.0
Name: ourLittleLogger
Version: 0.2.2
Summary: ourLittleLogger is used for logging unification.
Home-page: https://gitlab.com/benzolium/python-logger
Author: connectome.ai
Author-email: UNKNOWN
License: UNKNOWN
Platform: UNKNOWN
